[ {
  "exportId" : "3s2pygNETRCyxr9CURShtg",
  "name" : "location",
  "paramType" : {
    "exportId" : "nBJ9Ph0FQ9q_tRhzfzCINw",
    "name" : "SSFLocation"
  },
  "question" : "Which location is this request associated with?",
  "isSavedForTeam" : false,
  "isSavedForUser" : false
}, {
  "exportId" : "4_KddBXYTuKbl5z6H_Z7rQ",
  "name" : "location",
  "paramType" : {
    "exportId" : "un1P2zxETp2Gi6p6DxbD0A",
    "name" : "Location"
  },
  "question" : "Where did you see this?",
  "isSavedForTeam" : false,
  "isSavedForUser" : false
}, {
  "exportId" : "5PJ3AxhdRk2aQ-idojF3IQ",
  "name" : "briefDescription",
  "paramType" : {
    "exportId" : "Text",
    "name" : "Text"
  },
  "question" : "Briefly describe the issue",
  "isSavedForTeam" : false,
  "isSavedForUser" : false
}, {
  "exportId" : "74w_pwi1Sj-hr3f2cZ1weQ",
  "name" : "description",
  "paramType" : {
    "exportId" : "Text",
    "name" : "Text"
  },
  "question" : "What are you requesting? Provide a full description.",
  "isSavedForTeam" : false,
  "isSavedForUser" : false
}, {
  "exportId" : "7RE1_GqdSSGK8UPAJSPgpA",
  "name" : "urgency",
  "paramType" : {
    "exportId" : "XqH4g7GxQxOFUWbGHxnsBA",
    "name" : "Urgency"
  },
  "question" : "What is the urgency of this request? (For emergencies, please contact a member of maintenance or security)",
  "isSavedForTeam" : false,
  "isSavedForUser" : false
}, {
  "exportId" : "C_X0ab3UQvu1FtcNXqAJcA",
  "name" : "location",
  "paramType" : {
    "exportId" : "un1P2zxETp2Gi6p6DxbD0A",
    "name" : "Location"
  },
  "question" : "Which location is this request associated with?",
  "isSavedForTeam" : false,
  "isSavedForUser" : false
}, {
  "exportId" : "E9qDlXL8Qyi-jY7OSaGWJw",
  "name" : "concernLevel",
  "paramType" : {
    "exportId" : "w6FA6MKdTXumxpQXOeUa4w",
    "name" : "ConcernLevel"
  },
  "question" : "How concerned are you about the issue?",
  "isSavedForTeam" : false,
  "isSavedForUser" : false
}, {
  "exportId" : "EqGpy5hYSsilEf8u0JzIMA",
  "name" : "file",
  "paramType" : {
    "exportId" : "File",
    "name" : "File"
  },
  "question" : "Paste an image or upload a file that shows the problem",
  "isSavedForTeam" : false,
  "isSavedForUser" : false
}, {
  "exportId" : "NH5AE9TdTP-B5GSD5yOXVQ",
  "name" : "details",
  "paramType" : {
    "exportId" : "Text",
    "name" : "Text"
  },
  "question" : "Add any additional details you'd like to include, or type \"none\"",
  "isSavedForTeam" : false,
  "isSavedForUser" : false
}, {
  "exportId" : "POGjGINhTX6rJyiD4z31rw",
  "name" : "notes",
  "paramType" : {
    "exportId" : "Text",
    "name" : "Text"
  },
  "question" : "Any other special notes? (or type 'none')",
  "isSavedForTeam" : false,
  "isSavedForUser" : false
}, {
  "exportId" : "QE8taVcuQSC8N9qQ2q0Xvw",
  "name" : "department",
  "paramType" : {
    "exportId" : "Text",
    "name" : "Text"
  },
  "question" : "What department of the company is this request associated with?",
  "isSavedForTeam" : false,
  "isSavedForUser" : false
}, {
  "exportId" : "dJ3rjV2gSxG7Grjj3PgzaQ",
  "name" : "workOrderId",
  "paramType" : {
    "exportId" : "Text",
    "name" : "Text"
  },
  "question" : "For which work order ID?",
  "isSavedForTeam" : false,
  "isSavedForUser" : false
}, {
  "exportId" : "dzoLcBpLSkez7HGFJdUfRA",
  "name" : "location",
  "paramType" : {
    "exportId" : "vdhbyVP4Qum76ZELpep98A",
    "name" : "LARLocation"
  },
  "question" : "Which location is this request associated with?",
  "isSavedForTeam" : false,
  "isSavedForUser" : false
}, {
  "exportId" : "ijULX9nbTVS5uBcI4ymvwQ",
  "name" : "userId",
  "paramType" : {
    "exportId" : "Text",
    "name" : "Text"
  },
  "question" : "What is the value for `userId`?",
  "isSavedForTeam" : false,
  "isSavedForUser" : false
}, {
  "exportId" : "nRdLTJtUThaLPwLtgIplng",
  "name" : "file",
  "paramType" : {
    "exportId" : "File",
    "name" : "File"
  },
  "question" : "File?",
  "isSavedForTeam" : false,
  "isSavedForUser" : false
}, {
  "exportId" : "tZZZJ9zxToGGmhHbZixJ6Q",
  "name" : "stillUnsafe",
  "paramType" : {
    "exportId" : "Yes/No",
    "name" : "Yes/No"
  },
  "question" : "Is the situation still unsafe?",
  "isSavedForTeam" : false,
  "isSavedForUser" : false
}, {
  "exportId" : "wTrGBEsdQc6hgCCSB4360A",
  "name" : "hazardType",
  "paramType" : {
    "exportId" : "42CuJUqkQhC1xaTNDffe6w",
    "name" : "HazardType"
  },
  "question" : "What type of hazard is it?",
  "isSavedForTeam" : false,
  "isSavedForUser" : false
} ]